fishingeffort
venv
