Metadata-Version: 2.4
Name: fishingeffort
Version: 0.1.1
Summary: Estimate and analyze fishing effort using geographical position of vessels (AIS or VMS)
Author-email: Sarah Paradis <sarah.paradisvilar@gmail.com>
License: MIT
Project-URL: Homepage, https://github.com/sarah-paradis/fishingeffort
Project-URL: Repository, https://github.com/sarah-paradis/fishingeffort
Classifier: Development Status :: 4 - Beta
Classifier: Intended Audience :: Science/Research
Classifier: Topic :: Scientific/Engineering :: Information Analysis
Classifier: License :: OSI Approved :: MIT License
Classifier: Programming Language :: Python :: 3
Classifier: Programming Language :: Python :: 3.7
Classifier: Programming Language :: Python :: 3.8
Classifier: Programming Language :: Python :: 3.9
Classifier: Operating System :: OS Independent
Requires-Python: >=3.7
License-File: LICENSE
Requires-Dist: pandas
Requires-Dist: numpy
Requires-Dist: geopandas
Requires-Dist: geocube
Requires-Dist: scipy
Requires-Dist: cartopy
Requires-Dist: rasterio
Requires-Dist: seaborn
Dynamic: license-file
